ocs_archive/__init__.py
ocs_archive/input/__init__.py
ocs_archive/input/file.py
ocs_archive/input/filefactory.py
ocs_archive/input/fitsfile.py
ocs_archive/input/headerdata.py
ocs_archive/input/lcofitsfile.py
ocs_archive/input/lcotarwithfitsfile.py
ocs_archive/input/tarwithfitsfile.py
ocs_archive/input/thumbnailfile.py
ocs_archive/settings/__init__.py
ocs_archive/settings/settings.py
ocs_archive/storage/__init__.py
ocs_archive/storage/filestore.py
ocs_archive/storage/filestorefactory.py
ocs_archive/storage/filesystemstore.py
ocs_archive/storage/s3store.py
ocs_archive-0.4.0.dist-info/LICENSE
ocs_archive-0.4.0.dist-info/METADATA
ocs_archive-0.4.0.dist-info/WHEEL
ocs_archive-0.4.0.dist-info/RECORD
