Metadata-Version: 2.1
Name: ocs-archive
Version: 0.4.0
Summary: Base library for the science archive and ingester of an observatory control system
Home-page: https://observatorycontrolsystem.github.io
License: GPL-3.0-only
Keywords: observations,astronomy,astrophysics,cosmology,science
Author: Observatory Control System Project
Author-email: ocs@lco.global
Requires-Python: >=3.8
Classifier: Development Status :: 3 - Alpha
Classifier: Intended Audience :: Science/Research
Classifier: License :: OSI Approved :: GNU General Public License v3 (GPLv3)
Classifier: Operating System :: OS Independent
Classifier: Programming Language :: Python :: 3
Classifier: Programming Language :: Python :: 3.8
Classifier: Programming Language :: Python :: 3.9
Classifier: Programming Language :: Python :: 3.10
Classifier: Programming Language :: Python :: 3.11
Classifier: Programming Language :: Python :: 3.12
Classifier: Topic :: Scientific/Engineering :: Astronomy
Classifier: Topic :: Scientific/Engineering :: Physics
Requires-Dist: astropy (>=3,<6)
Requires-Dist: boto3 (>=1,<2)
Requires-Dist: python-dateutil (>=2,<3)
Requires-Dist: requests (>=2,<3)
Project-URL: Repository, https://github.com/observatorycontrolsystem/ocs_archive
